README.md
setup.py
topsis/cli.py
topsis/tops.py
topsis_hitesh.egg-info/PKG-INFO
topsis_hitesh.egg-info/SOURCES.txt
topsis_hitesh.egg-info/dependency_links.txt
topsis_hitesh.egg-info/entry_points.txt
topsis_hitesh.egg-info/requires.txt
topsis_hitesh.egg-info/top_level.txt