Metadata-Version: 2.1
Name: topsis-hitesh
Version: 1.0.0
Summary: A Python package to implement Topsis analysis
Home-page: https://github.com/Hiteshgupta98/topsis-hiteshgupta
Author: Hitesh Gupta
Author-email: phoenixhitesh8@gmail.com
License: MIT
Platform: UNKNOWN
Classifier: License :: OSI Approved :: MIT License
Classifier: Programming Language :: Python :: 3
Classifier: Programming Language :: Python :: 3.7
